LICENSE
MANIFEST.in
README.md
noxfile.py
pyproject.toml
setup.cfg
.github/matchers/pylint.json
.github/workflows/ci.yml
src/exclusion/__init__.py
src/exclusion/_version.py
src/exclusion/_version.pyi
src/exclusion/interpolate.py
src/exclusion/py.typed
src/exclusion/visualize.py
src/exclusion.egg-info/PKG-INFO
src/exclusion.egg-info/SOURCES.txt
src/exclusion.egg-info/dependency_links.txt
src/exclusion.egg-info/requires.txt
src/exclusion.egg-info/top_level.txt
tests/test_package.py