Metadata-Version: 2.1
Name: exclusion
Version: 0.0.1
Summary: Calculate and visualize exclusion contours
Home-page: https://github.com/matthewfeickert/exclusion
Author: Matthew Feickert
Author-email: matthew.feickert@cern.ch
Maintainer: Matthew Feickert
Maintainer-email: matthew.feickert@cern.ch
License: BSD-3-Clause
Project-URL: Documentation, https://exclusion.readthedocs.io/
Project-URL: Bug Tracker, https://github.com/matthewfeickert/exclusion/issues
Project-URL: Discussions, https://github.com/matthewfeickert/exclusion/discussions
Project-URL: Changelog, https://github.com/matthewfeickert/exclusion/releases
Platform: Any
Classifier: Development Status :: 1 - Planning
Classifier: Intended Audience :: Developers
Classifier: Intended Audience :: Science/Research
Classifier: License :: OSI Approved :: BSD License
Classifier: Operating System :: OS Independent
Classifier: Programming Language :: Python
Classifier: Programming Language :: Python :: 3
Classifier: Programming Language :: Python :: 3 :: Only
Classifier: Programming Language :: Python :: 3.7
Classifier: Programming Language :: Python :: 3.8
Classifier: Programming Language :: Python :: 3.9
Classifier: Programming Language :: Python :: 3.10
Classifier: Topic :: Scientific/Engineering
Requires-Python: >=3.7
Provides-Extra: dev
Provides-Extra: docs
Provides-Extra: test
License-File: LICENSE
